jsonstat_validator/__init__.py
jsonstat_validator/models/__init__.py
jsonstat_validator/models/base.py
jsonstat_validator/models/category.py
jsonstat_validator/models/collection.py
jsonstat_validator/models/dataset.py
jsonstat_validator/models/dimension.py
jsonstat_validator/models/link.py
jsonstat_validator/models/unit.py
jsonstat_validator/utils.py
jsonstat_validator/validator.py
jsonstat_validator-0.4.5.dist-info/WHEEL
jsonstat_validator-0.4.5.dist-info/METADATA
jsonstat_validator-0.4.5.dist-info/RECORD
