Metadata-Version: 2.3
Name: jsonstat-validator
Version: 0.4.5
Summary: A Python validator for the JSON-stat 2.0 standard format, based on Pydantic.
Keywords: json-stat,validator,json,data-engineering,pydantic,python,fao
Author: Ahmed Hassan
Author-email: Ahmed Hassan <ahmedhassan.ahmed@fao.org>
License: # MIT License
Classifier: Programming Language :: Python :: 3
Classifier: Programming Language :: Python :: 3.11
Classifier: Programming Language :: Python :: 3.12
Classifier: Programming Language :: Python :: 3.13
Classifier: License :: OSI Approved :: MIT License
Classifier: Operating System :: OS Independent
Classifier: Topic :: Software Development :: Libraries :: Python Modules
Classifier: Topic :: Software Development :: Quality Assurance
Requires-Dist: pydantic>=2.11.9
Requires-Dist: pytest>=8.4.2 ; extra == 'dev'
Requires-Dist: pytest-cov>=7.0.0 ; extra == 'dev'
Requires-Dist: pre-commit>=4.3.0 ; extra == 'dev'
Requires-Dist: ruff>=0.13.2 ; extra == 'dev'
Requires-Python: >=3.11
Project-URL: Bug Tracker, https://github.com/ahmed-hassan19/jsonstat-validator/issues
Project-URL: Documentation, https://github.com/ahmed-hassan19/jsonstat-validator#readme
Project-URL: Homepage, https://github.com/ahmed-hassan19/jsonstat-validator
Provides-Extra: dev
